setup.py
rattlesnake/__init__.py
rattlesnake/dispatcher.py
rattlesnake/request.py
rattlesnake/response.py
rattlesnake.egg-info/PKG-INFO
rattlesnake.egg-info/SOURCES.txt
rattlesnake.egg-info/dependency_links.txt
rattlesnake.egg-info/not-zip-safe
rattlesnake.egg-info/top_level.txt
rattlesnake/handlers/__init__.py