Metadata-Version: 1.0
Name: rattlesnake
Version: 0.0.1
Summary: dangerous web framework
Home-page: http://rattlesnake.tplus1.com
Author: Matt Wilson
Author-email: matt@tplus1.com
License: BSD
Keywords: rattlesnake
Platform: UNKNOWN
